<?xml version = '1.0' encoding = 'UTF-8'?>
<Relation class="oracle.dbtools.crest.model.design.logical.Relation" name="meci_turneu" directorySegmentName="seg_0" id="F4B3CD74-000B-DC56-5AEB-7371ACCAF5B3">
<createdBy>root</createdBy>
<createdTime>2025-05-15 09:33:33 UTC</createdTime>
<ownerDesignName>esports2</ownerDesignName>
<importedID>39B5508B-51F3-83BE-0AFE-278416C87C69</importedID>
<engineerTo>
<item key="65C58082-46EC-FB76-2B2A-9B317DB3C1B6" value="true"/>
<item key="D1223DF1-1933-12C0-E9F1-820D710E5648" value="true"/>
</engineerTo>
<sourcePk>FDB161B3-145F-92A5-6BD4-7B98C1445D64</sourcePk>
<identifying>false</identifying>
<optionalSource>true</optionalSource>
<optionalTarget>false</optionalTarget>
<sourceCardinality>1</sourceCardinality>
<sourceEntity>259919C8-920B-7D53-F800-F908A13F99E5</sourceEntity>
<targetCardinalityString>1</targetCardinalityString>
<targetEntity>CF760705-0C05-1873-7866-3B0DC9C29A82</targetEntity>
<transferable>true</transferable>
<deleteRule>NO ACTION</deleteRule>
</Relation>